folketinget/__init__.py
folketinget/client.py
folketinget-0.1.0.dist-info/METADATA
folketinget-0.1.0.dist-info/WHEEL
folketinget-0.1.0.dist-info/entry_points.txt
folketinget-0.1.0.dist-info/RECORD
