Metadata-Version: 2.4
Name: folketinget
Version: 0.1.0
Summary: Intuitive client for the Danish Parliament API.
Author-email: Kasper Junge <kasperjuunge@gmail.com>
Requires-Python: >=3.12
Requires-Dist: requests>=2.32.3
